LICENSE.txt
MANIFEST.in
README.rst
setup.py
Flask_FlatPages_Pandoc.egg-info/PKG-INFO
Flask_FlatPages_Pandoc.egg-info/SOURCES.txt
Flask_FlatPages_Pandoc.egg-info/dependency_links.txt
Flask_FlatPages_Pandoc.egg-info/requires.txt
Flask_FlatPages_Pandoc.egg-info/top_level.txt
flask_flatpages_pandoc/__init__.py