Metadata-Version: 1.1
Name: Flask-FlatPages-Pandoc
Version: 0.2
Summary: Pandoc rendering for Flask-FlatPages
Home-page: http://github.com/fhirschmann/Flask-FlatPages-Pandoc
Author: Fabian Hirschmann
Author-email: fabian@hirschm.net
License: MIT
Keywords: flask flatpages pandoc latex markdown
Platform: any
Classifier: Development Status :: 3 - Alpha
Classifier: Environment :: Web Environment
Classifier: Intended Audience :: Developers
Classifier: License :: OSI Approved :: MIT License
Classifier: Operating System :: OS Independent
Classifier: Framework :: Flask
Classifier: Programming Language :: Python
Classifier: Topic :: Internet :: WWW/HTTP :: Dynamic Content
Classifier: Topic :: Software Development :: Libraries :: Python Modules
Classifier: Programming Language :: Python :: 2
Classifier: Programming Language :: Python :: 2.5
Classifier: Programming Language :: Python :: 2.6
Classifier: Programming Language :: Python :: 2.7
